apiintercambiador.py
apiintercambiador-0.0.4.dist-info/METADATA
apiintercambiador-0.0.4.dist-info/WHEEL
apiintercambiador-0.0.4.dist-info/top_level.txt
apiintercambiador-0.0.4.dist-info/RECORD
