Metadata-Version: 2.1
Name: apiintercambiador
Version: 0.0.4
Summary: Librería para transferir información entre API Intercambiador y las fuentes de datos.
Home-page: UNKNOWN
Author: Marc Güell Jiménez
Author-email: mguell@tridenia.com
License: MIT
Platform: UNKNOWN
Requires-Dist: requests
